sftp/__init__.py
sftp/ftp.py
shttp/__init__.py
shttp/handler.py
shttp-0.3.0.dist-info/AUTHORS
shttp-0.3.0.dist-info/METADATA
shttp-0.3.0.dist-info/WHEEL
shttp-0.3.0.dist-info/pbr.json
shttp-0.3.0.dist-info/top_level.txt
shttp-0.3.0.dist-info/RECORD
